setup.py
corenode/__init__.py
corenode/app.py
corenode/settings.py
corenode/urls.py
corenode.egg-info/PKG-INFO
corenode.egg-info/SOURCES.txt
corenode.egg-info/dependency_links.txt
corenode.egg-info/requires.txt
corenode.egg-info/top_level.txt
corenode/hooks/__init__.py
corenode/hooks/network_vxlan.py
corenode/hooks/vm.py