Metadata-Version: 1.1
Name: corenode
Version: 17.4.1
Summary: CoreCluster node configuration and management package
Home-page: http://cloudover.org/corecluster/
Author: Marta Nabozny
Author-email: martastrzet@gmail.com
License: UNKNOWN
Download-URL: https://github.com/cloudOver/CoreNode/archive/master.zip
Keywords: corecluster,cloudover,cloud
Platform: UNKNOWN
